parakeet/__init__.py
parakeet/audio/__init__.py
parakeet/audio/audio.py
parakeet/audio/spec_normalizer.py
parakeet/data/__init__.py
parakeet/data/batch.py
parakeet/data/dataset.py
parakeet/datasets/__init__.py
parakeet/datasets/common.py
parakeet/datasets/ljspeech.py
parakeet/frontend/__init__.py
parakeet/frontend/arpabet.py
parakeet/frontend/phonectic.py
parakeet/frontend/pinyin.py
parakeet/frontend/punctuation.py
parakeet/frontend/vocab.py
parakeet/frontend/normalizer/__init__.py
parakeet/frontend/normalizer/abbrrviation.py
parakeet/frontend/normalizer/acronyms.py
parakeet/frontend/normalizer/normalizer.py
parakeet/frontend/normalizer/numbers.py
parakeet/frontend/normalizer/width.py
parakeet/models/__init__.py
parakeet/models/lstm_speaker_encoder.py
parakeet/models/tacotron2.py
parakeet/models/transformer_tts.py
parakeet/models/waveflow.py
parakeet/models/wavenet.py
parakeet/modules/__init__.py
parakeet/modules/attention.py
parakeet/modules/audio.py
parakeet/modules/conv.py
parakeet/modules/geometry.py
parakeet/modules/losses.py
parakeet/modules/masking.py
parakeet/modules/positional_encoding.py
parakeet/modules/transformer.py
parakeet/training/__init__.py
parakeet/training/cli.py
parakeet/training/default_config.py
parakeet/training/experiment.py
parakeet/training/reporter.py
parakeet/training/trainer.py
parakeet/training/trigger.py
parakeet/training/updater.py
parakeet/utils/__init__.py
parakeet/utils/checkpoint.py
parakeet/utils/display.py
parakeet/utils/internals.py
parakeet/utils/layer_tools.py
parakeet/utils/mp_tools.py
parakeet/utils/scheduler.py
paddle_parakeet-0.3.1.dist-info/LICENSE
paddle_parakeet-0.3.1.dist-info/METADATA
paddle_parakeet-0.3.1.dist-info/WHEEL
paddle_parakeet-0.3.1.dist-info/top_level.txt
paddle_parakeet-0.3.1.dist-info/zip-safe
paddle_parakeet-0.3.1.dist-info/RECORD
