Metadata-Version: 2.1
Name: paddle-parakeet
Version: 0.3.1
Summary: Speech synthesis tools and models based on Paddlepaddle
Home-page: https://github.com/PaddlePaddle
Author: PaddleSL Team
Author-email: 
License: Apache 2
Platform: UNKNOWN
Classifier: Development Status :: 4 - Beta
Classifier: Intended Audience :: Developers
Classifier: Intended Audience :: Science/Research
Classifier: Topic :: Scientific/Engineering :: Artificial Intelligence
Classifier: License :: OSI Approved :: Apache Software License
Classifier: Programming Language :: Python :: 3.6
Classifier: Programming Language :: Python :: 3.7
Requires-Python: >=3.6
Requires-Dist: numpy
Requires-Dist: nltk
Requires-Dist: inflect
Requires-Dist: librosa
Requires-Dist: unidecode
Requires-Dist: numba
Requires-Dist: tqdm
Requires-Dist: llvmlite
Requires-Dist: matplotlib
Requires-Dist: visualdl (>=2.0.1)
Requires-Dist: scipy
Requires-Dist: pandas
Requires-Dist: sox
Requires-Dist: soundfile
Requires-Dist: g2p-en
Requires-Dist: yacs
Requires-Dist: visualdl
Requires-Dist: pypinyin
Requires-Dist: webrtcvad
Requires-Dist: g2pM
Requires-Dist: praatio
Provides-Extra: doc
Requires-Dist: sphinx ; extra == 'doc'
Requires-Dist: sphinx-rtd-theme ; extra == 'doc'
Requires-Dist: numpydoc ; extra == 'doc'
